dsci_310_group_10_package/.ipynb_checkpoints/alpha_tuning-checkpoint.py
dsci_310_group_10_package/.ipynb_checkpoints/inv_outcome_plot-checkpoint.py
dsci_310_group_10_package/KNN_tuning.py
dsci_310_group_10_package/__init__.py
dsci_310_group_10_package/alpha_tuning.py
dsci_310_group_10_package/format_histograms.py
dsci_310_group_10_package/inv_outcome_plot.py
dsci_310_group_10_package/split_drop.py
dsci_310_group_10_package-0.2.1.dist-info/LICENSE
dsci_310_group_10_package-0.2.1.dist-info/WHEEL
dsci_310_group_10_package-0.2.1.dist-info/METADATA
dsci_310_group_10_package-0.2.1.dist-info/RECORD
