Metadata-Version: 2.1
Name: dsci-310-group-10-package
Version: 0.2.1
Summary: This package contains the functions for the Statistics Canada investment income analysis,by group 10
License: MIT
Author: Harry Zhang Ahmed Rizk Mahdi Heydar Nikko Dumrique
Requires-Python: >=3.9,<3.10
Classifier: License :: OSI Approved :: MIT License
Classifier: Programming Language :: Python :: 3
Classifier: Programming Language :: Python :: 3.9
Requires-Dist: docopt (>=0.6.2,<0.7.0)
Requires-Dist: jupyterlab (>=3.3.2,<4.0.0)
Requires-Dist: matplotlib (>=3.5.1,<4.0.0)
Requires-Dist: numpy (>=1.22.3,<2.0.0)
Requires-Dist: pandas (>=1.4.2,<2.0.0)
Requires-Dist: pytest (>=7.1.1,<8.0.0)
Requires-Dist: scikit-learn (>=1.0.2,<2.0.0)
Requires-Dist: seaborn (>=0.11.2,<0.12.0)
